sqlalchemy_collectd/__init__.py
sqlalchemy_collectd/collectd_types.py
sqlalchemy_collectd/protocol.py
sqlalchemy_collectd/stream.py
sqlalchemy_collectd/testing.py
sqlalchemy_collectd/client/__init__.py
sqlalchemy_collectd/client/collector.py
sqlalchemy_collectd/client/plugin.py
sqlalchemy_collectd/client/sender.py
sqlalchemy_collectd/client/worker.py
sqlalchemy_collectd/client/tests/__init__.py
sqlalchemy_collectd/client/tests/test_collector.py
sqlalchemy_collectd/client/tests/test_plugin.py
sqlalchemy_collectd/client/tests/test_worker.py
sqlalchemy_collectd/connmon/__init__.py
sqlalchemy_collectd/connmon/display.py
sqlalchemy_collectd/connmon/main.py
sqlalchemy_collectd/connmon/plugin.py
sqlalchemy_collectd/connmon/stat.py
sqlalchemy_collectd/connmon/util.py
sqlalchemy_collectd/server/__init__.py
sqlalchemy_collectd/server/listener.py
sqlalchemy_collectd/server/logging.py
sqlalchemy_collectd/server/plugin.py
sqlalchemy_collectd/server/receiver.py
sqlalchemy_collectd/server/tests/__init__.py
sqlalchemy_collectd/server/tests/test_listener.py
sqlalchemy_collectd/tests/__init__.py
sqlalchemy_collectd/tests/test_protocol.py
sqlalchemy_collectd/tests/test_stream.py
sqlalchemy_collectd/tests/test_time_bucket.py
sqlalchemy_collectd-0.0.8.dist-info/LICENSE
sqlalchemy_collectd-0.0.8.dist-info/METADATA
sqlalchemy_collectd-0.0.8.dist-info/WHEEL
sqlalchemy_collectd-0.0.8.dist-info/entry_points.txt
sqlalchemy_collectd-0.0.8.dist-info/top_level.txt
sqlalchemy_collectd-0.0.8.dist-info/RECORD
