Metadata-Version: 2.1
Name: sqlalchemy-collectd
Version: 0.0.8
Summary: Send database connection pool stats to collectd
Home-page: https://github.com/sqlalchemy/sqlalchemy-collectd
Author: Mike Bayer
Author-email: mike@zzzcomputing.com
License: MIT
Keywords: SQLAlchemy collectd
Platform: UNKNOWN
Classifier: Development Status :: 3 - Alpha
Classifier: Intended Audience :: Developers
Classifier: Programming Language :: Python
Classifier: Programming Language :: Python :: 3
Classifier: Topic :: Database :: Front-Ends
License-File: LICENSE
Requires-Dist: SQLAlchemy (>=1.1)
